OpenstackCloudMonitoringAPI/CloudUsage.py
OpenstackCloudMonitoringAPI/__init__.py
OpenstackCloudMonitoringAPI/constants.py
OpenstackCloudMonitoringAPI/ttypes.py
OpenstackMonitoringAPI-0.1.0.dev15.dist-info/DESCRIPTION.rst
OpenstackMonitoringAPI-0.1.0.dev15.dist-info/METADATA
OpenstackMonitoringAPI-0.1.0.dev15.dist-info/RECORD
OpenstackMonitoringAPI-0.1.0.dev15.dist-info/WHEEL
OpenstackMonitoringAPI-0.1.0.dev15.dist-info/metadata.json
OpenstackMonitoringAPI-0.1.0.dev15.dist-info/top_level.txt
